abimap/__init__.py
abimap/_version.py
abimap/main.py
abimap/symver.py
abimap-0.4.0.dist-info/licenses/AUTHORS.rst
abimap-0.4.0.dist-info/licenses/LICENSE
abimap-0.4.0.dist-info/METADATA
abimap-0.4.0.dist-info/WHEEL
abimap-0.4.0.dist-info/entry_points.txt
abimap-0.4.0.dist-info/top_level.txt
abimap-0.4.0.dist-info/RECORD
