Metadata-Version: 2.4
Name: abimap
Version: 0.4.0
Summary: A helper for library maintainers to use symbol versioning
Home-page: https://github.com/ansasaki/abimap
Author: Anderson Toshiyuki Sasaki
Author-email: Anderson Toshiyuki Sasaki <ansasaki@redhat.com>
License-Expression: MIT
Project-URL: homepage, https://github.com/ansasaki/abimap
Keywords: symver,abimap,symbol,version,versioning,linker,script,library,maintenance
Classifier: Development Status :: 2 - Pre-Alpha
Classifier: Intended Audience :: Developers
Classifier: Topic :: Software Development :: Build Tools
Classifier: Natural Language :: English
Classifier: Programming Language :: Python :: 3
Classifier: Programming Language :: Python :: 3.9
Classifier: Programming Language :: Python :: 3.10
Classifier: Programming Language :: Python :: 3.11
Classifier: Programming Language :: Python :: 3.12
Classifier: Programming Language :: Python :: 3.13
Requires-Python: >=3.9
License-File: LICENSE
License-File: AUTHORS.rst
Requires-Dist: setuptools
Provides-Extra: dev
Requires-Dist: flake8; extra == "dev"
Requires-Dist: build; extra == "dev"
Requires-Dist: sphinx>=6.0.0; extra == "dev"
Requires-Dist: sphinx-rtd-theme>=1.2.0; extra == "dev"
Requires-Dist: watchdog>=2.0.0; extra == "dev"
Provides-Extra: test
Requires-Dist: pytest; extra == "test"
Requires-Dist: pyyaml; extra == "test"
Requires-Dist: pytest-cov; extra == "test"
Requires-Dist: pytest-console-scripts; extra == "test"
Dynamic: author
Dynamic: home-page
Dynamic: license-file
